[
  {
    "id": 1,
    "Company": "Nasdaq 100",
    "Stock": "QQQ"
  },
  {
    "id": 2,
    "Company": "Healthcare",
    "Stock": "XLV"
  },
  {
    "id": 3,
    "Company": "SaaS",
    "Stock": "IGV"
  },
  {
    "id": 4,
    "Company": "Speculative Biotech",
    "Stock": "XBI"
  },
  {
    "id": 5,
    "Company": "Energy",
    "Stock": "XLE"
  },
  {
    "id": 6,
    "Company": "Small Caps",
    "Stock": "IWM"
  },
  {
    "id": 7,
    "Company": "China 25",
    "Stock": "FXI"
  },
  {
    "id": 8,
    "Company": "Semiconductors",
    "Stock": "SMH"
  },
  {
    "id": 9,
    "Company": "Microcaps",
    "Stock": "IWC"
  }
]
